{"nodes": [{"id": "c_users_hp_onedrive_desktop_projects_vs_code_arocord_hims_care_harmony_hub_docs_development_standards_md", "label": "DEVELOPMENT_STANDARDS.md", "file_type": "document", "source_file": "C:\\Users\\HP\\OneDrive\\Desktop\\Projects\\VS Code\\AroCord-HIMS\\care-harmony-hub\\docs\\DEVELOPMENT_STANDARDS.md", "source_location": "L1"}, {"id": "docs_development_standards_caresync_hims_development_standards_best_practices", "label": "CareSync HIMS - Development Standards & Best Practices", "file_type": "document", "source_file": "C:\\Users\\HP\\OneDrive\\Desktop\\Projects\\VS Code\\AroCord-HIMS\\care-harmony-hub\\docs\\DEVELOPMENT_STANDARDS.md", "source_location": "L1"}, {"id": "docs_development_standards_quick_navigation", "label": "\ud83d\udcda Quick Navigation", "file_type": "document", "source_file": "C:\\Users\\HP\\OneDrive\\Desktop\\Projects\\VS Code\\AroCord-HIMS\\care-harmony-hub\\docs\\DEVELOPMENT_STANDARDS.md", "source_location": "L9"}, {"id": "docs_development_standards_core_principles", "label": "\ud83c\udfaf Core Principles", "file_type": "document", "source_file": "C:\\Users\\HP\\OneDrive\\Desktop\\Projects\\VS Code\\AroCord-HIMS\\care-harmony-hub\\docs\\DEVELOPMENT_STANDARDS.md", "source_location": "L20"}, {"id": "docs_development_standards_1_clean_code_solid", "label": "1. **Clean Code & SOLID**", "file_type": "document", "source_file": "C:\\Users\\HP\\OneDrive\\Desktop\\Projects\\VS Code\\AroCord-HIMS\\care-harmony-hub\\docs\\DEVELOPMENT_STANDARDS.md", "source_location": "L22"}, {"id": "docs_development_standards_2_type_safety", "label": "2. **Type Safety**", "file_type": "document", "source_file": "C:\\Users\\HP\\OneDrive\\Desktop\\Projects\\VS Code\\AroCord-HIMS\\care-harmony-hub\\docs\\DEVELOPMENT_STANDARDS.md", "source_location": "L28"}, {"id": "docs_development_standards_3_error_handling_security", "label": "3. **Error Handling & Security**", "file_type": "document", "source_file": "C:\\Users\\HP\\OneDrive\\Desktop\\Projects\\VS Code\\AroCord-HIMS\\care-harmony-hub\\docs\\DEVELOPMENT_STANDARDS.md", "source_location": "L34"}, {"id": "docs_development_standards_4_performance", "label": "4. **Performance**", "file_type": "document", "source_file": "C:\\Users\\HP\\OneDrive\\Desktop\\Projects\\VS Code\\AroCord-HIMS\\care-harmony-hub\\docs\\DEVELOPMENT_STANDARDS.md", "source_location": "L40"}, {"id": "docs_development_standards_code_style_guide", "label": "\ud83d\udcdd Code Style Guide", "file_type": "document", "source_file": "C:\\Users\\HP\\OneDrive\\Desktop\\Projects\\VS Code\\AroCord-HIMS\\care-harmony-hub\\docs\\DEVELOPMENT_STANDARDS.md", "source_location": "L48"}, {"id": "docs_development_standards_typescript_configuration", "label": "TypeScript Configuration", "file_type": "document", "source_file": "C:\\Users\\HP\\OneDrive\\Desktop\\Projects\\VS Code\\AroCord-HIMS\\care-harmony-hub\\docs\\DEVELOPMENT_STANDARDS.md", "source_location": "L50"}, {"id": "docs_development_standards_codeblock_1", "label": "code:json ({)", "file_type": "document", "source_file": "C:\\Users\\HP\\OneDrive\\Desktop\\Projects\\VS Code\\AroCord-HIMS\\care-harmony-hub\\docs\\DEVELOPMENT_STANDARDS.md", "source_location": "L53"}, {"id": "docs_development_standards_naming_conventions", "label": "Naming Conventions", "file_type": "document", "source_file": "C:\\Users\\HP\\OneDrive\\Desktop\\Projects\\VS Code\\AroCord-HIMS\\care-harmony-hub\\docs\\DEVELOPMENT_STANDARDS.md", "source_location": "L68"}, {"id": "docs_development_standards_components", "label": "Components", "file_type": "document", "source_file": "C:\\Users\\HP\\OneDrive\\Desktop\\Projects\\VS Code\\AroCord-HIMS\\care-harmony-hub\\docs\\DEVELOPMENT_STANDARDS.md", "source_location": "L70"}, {"id": "docs_development_standards_codeblock_2", "label": "code:typescript (// \u2705 Descriptive PascalCase)", "file_type": "document", "source_file": "C:\\Users\\HP\\OneDrive\\Desktop\\Projects\\VS Code\\AroCord-HIMS\\care-harmony-hub\\docs\\DEVELOPMENT_STANDARDS.md", "source_location": "L71"}, {"id": "docs_development_standards_hooks", "label": "Hooks", "file_type": "document", "source_file": "C:\\Users\\HP\\OneDrive\\Desktop\\Projects\\VS Code\\AroCord-HIMS\\care-harmony-hub\\docs\\DEVELOPMENT_STANDARDS.md", "source_location": "L81"}, {"id": "docs_development_standards_codeblock_3", "label": "code:typescript (// \u2705 Clear domain + action)", "file_type": "document", "source_file": "C:\\Users\\HP\\OneDrive\\Desktop\\Projects\\VS Code\\AroCord-HIMS\\care-harmony-hub\\docs\\DEVELOPMENT_STANDARDS.md", "source_location": "L82"}, {"id": "docs_development_standards_types_interfaces", "label": "Types & Interfaces", "file_type": "document", "source_file": "C:\\Users\\HP\\OneDrive\\Desktop\\Projects\\VS Code\\AroCord-HIMS\\care-harmony-hub\\docs\\DEVELOPMENT_STANDARDS.md", "source_location": "L93"}, {"id": "docs_development_standards_codeblock_4", "label": "code:typescript (// \u2705 Descriptive names reflecting domain)", "file_type": "document", "source_file": "C:\\Users\\HP\\OneDrive\\Desktop\\Projects\\VS Code\\AroCord-HIMS\\care-harmony-hub\\docs\\DEVELOPMENT_STANDARDS.md", "source_location": "L94"}, {"id": "docs_development_standards_file_organization", "label": "File Organization", "file_type": "document", "source_file": "C:\\Users\\HP\\OneDrive\\Desktop\\Projects\\VS Code\\AroCord-HIMS\\care-harmony-hub\\docs\\DEVELOPMENT_STANDARDS.md", "source_location": "L111"}, {"id": "docs_development_standards_component_structure", "label": "Component Structure", "file_type": "document", "source_file": "C:\\Users\\HP\\OneDrive\\Desktop\\Projects\\VS Code\\AroCord-HIMS\\care-harmony-hub\\docs\\DEVELOPMENT_STANDARDS.md", "source_location": "L113"}, {"id": "docs_development_standards_codeblock_5", "label": "code:block5 (src/components/)", "file_type": "document", "source_file": "C:\\Users\\HP\\OneDrive\\Desktop\\Projects\\VS Code\\AroCord-HIMS\\care-harmony-hub\\docs\\DEVELOPMENT_STANDARDS.md", "source_location": "L114"}, {"id": "docs_development_standards_hooks_structure", "label": "Hooks Structure", "file_type": "document", "source_file": "C:\\Users\\HP\\OneDrive\\Desktop\\Projects\\VS Code\\AroCord-HIMS\\care-harmony-hub\\docs\\DEVELOPMENT_STANDARDS.md", "source_location": "L134"}, {"id": "docs_development_standards_codeblock_6", "label": "code:block6 (src/lib/hooks/)", "file_type": "document", "source_file": "C:\\Users\\HP\\OneDrive\\Desktop\\Projects\\VS Code\\AroCord-HIMS\\care-harmony-hub\\docs\\DEVELOPMENT_STANDARDS.md", "source_location": "L135"}, {"id": "docs_development_standards_utilities_structure", "label": "Utilities Structure", "file_type": "document", "source_file": "C:\\Users\\HP\\OneDrive\\Desktop\\Projects\\VS Code\\AroCord-HIMS\\care-harmony-hub\\docs\\DEVELOPMENT_STANDARDS.md", "source_location": "L144"}, {"id": "docs_development_standards_codeblock_7", "label": "code:block7 (src/utils/)", "file_type": "document", "source_file": "C:\\Users\\HP\\OneDrive\\Desktop\\Projects\\VS Code\\AroCord-HIMS\\care-harmony-hub\\docs\\DEVELOPMENT_STANDARDS.md", "source_location": "L145"}, {"id": "docs_development_standards_react_component_patterns", "label": "\ud83c\udfa8 React Component Patterns", "file_type": "document", "source_file": "C:\\Users\\HP\\OneDrive\\Desktop\\Projects\\VS Code\\AroCord-HIMS\\care-harmony-hub\\docs\\DEVELOPMENT_STANDARDS.md", "source_location": "L154"}, {"id": "docs_development_standards_functional_component_with_hooks", "label": "Functional Component with Hooks", "file_type": "document", "source_file": "C:\\Users\\HP\\OneDrive\\Desktop\\Projects\\VS Code\\AroCord-HIMS\\care-harmony-hub\\docs\\DEVELOPMENT_STANDARDS.md", "source_location": "L156"}, {"id": "docs_development_standards_codeblock_8", "label": "code:typescript (// \u2705 GOOD: Clear, concise, type-safe)", "file_type": "document", "source_file": "C:\\Users\\HP\\OneDrive\\Desktop\\Projects\\VS Code\\AroCord-HIMS\\care-harmony-hub\\docs\\DEVELOPMENT_STANDARDS.md", "source_location": "L158"}, {"id": "docs_development_standards_form_component_with_validation", "label": "Form Component with Validation", "file_type": "document", "source_file": "C:\\Users\\HP\\OneDrive\\Desktop\\Projects\\VS Code\\AroCord-HIMS\\care-harmony-hub\\docs\\DEVELOPMENT_STANDARDS.md", "source_location": "L181"}, {"id": "docs_development_standards_codeblock_9", "label": "code:typescript (export function MedicationOrderForm({ prescriptionId }: Prop)", "file_type": "document", "source_file": "C:\\Users\\HP\\OneDrive\\Desktop\\Projects\\VS Code\\AroCord-HIMS\\care-harmony-hub\\docs\\DEVELOPMENT_STANDARDS.md", "source_location": "L184"}, {"id": "docs_development_standards_data_fetching_state_management", "label": "\ud83d\udd27 Data Fetching & State Management", "file_type": "document", "source_file": "C:\\Users\\HP\\OneDrive\\Desktop\\Projects\\VS Code\\AroCord-HIMS\\care-harmony-hub\\docs\\DEVELOPMENT_STANDARDS.md", "source_location": "L211"}, {"id": "docs_development_standards_using_tanstack_query_react_query", "label": "Using TanStack Query (React Query)", "file_type": "document", "source_file": "C:\\Users\\HP\\OneDrive\\Desktop\\Projects\\VS Code\\AroCord-HIMS\\care-harmony-hub\\docs\\DEVELOPMENT_STANDARDS.md", "source_location": "L213"}, {"id": "docs_development_standards_codeblock_10", "label": "code:typescript (// \u2705 Custom hook with TanStack Query)", "file_type": "document", "source_file": "C:\\Users\\HP\\OneDrive\\Desktop\\Projects\\VS Code\\AroCord-HIMS\\care-harmony-hub\\docs\\DEVELOPMENT_STANDARDS.md", "source_location": "L215"}, {"id": "docs_development_standards_error_handling", "label": "Error Handling", "file_type": "document", "source_file": "C:\\Users\\HP\\OneDrive\\Desktop\\Projects\\VS Code\\AroCord-HIMS\\care-harmony-hub\\docs\\DEVELOPMENT_STANDARDS.md", "source_location": "L243"}, {"id": "docs_development_standards_codeblock_11", "label": "code:typescript (// \u2705 Proper Error Handling)", "file_type": "document", "source_file": "C:\\Users\\HP\\OneDrive\\Desktop\\Projects\\VS Code\\AroCord-HIMS\\care-harmony-hub\\docs\\DEVELOPMENT_STANDARDS.md", "source_location": "L245"}, {"id": "docs_development_standards_security_hipaa", "label": "\ud83d\udd10 Security & HIPAA", "file_type": "document", "source_file": "C:\\Users\\HP\\OneDrive\\Desktop\\Projects\\VS Code\\AroCord-HIMS\\care-harmony-hub\\docs\\DEVELOPMENT_STANDARDS.md", "source_location": "L273"}, {"id": "docs_development_standards_input_sanitization", "label": "Input Sanitization", "file_type": "document", "source_file": "C:\\Users\\HP\\OneDrive\\Desktop\\Projects\\VS Code\\AroCord-HIMS\\care-harmony-hub\\docs\\DEVELOPMENT_STANDARDS.md", "source_location": "L275"}, {"id": "docs_development_standards_codeblock_12", "label": "code:typescript (// \u2705 Always sanitize user input)", "file_type": "document", "source_file": "C:\\Users\\HP\\OneDrive\\Desktop\\Projects\\VS Code\\AroCord-HIMS\\care-harmony-hub\\docs\\DEVELOPMENT_STANDARDS.md", "source_location": "L277"}, {"id": "docs_development_standards_phi_protection", "label": "PHI Protection", "file_type": "document", "source_file": "C:\\Users\\HP\\OneDrive\\Desktop\\Projects\\VS Code\\AroCord-HIMS\\care-harmony-hub\\docs\\DEVELOPMENT_STANDARDS.md", "source_location": "L287"}, {"id": "docs_development_standards_codeblock_13", "label": "code:typescript (// \u2705 Use encryption hooks for sensitive data)", "file_type": "document", "source_file": "C:\\Users\\HP\\OneDrive\\Desktop\\Projects\\VS Code\\AroCord-HIMS\\care-harmony-hub\\docs\\DEVELOPMENT_STANDARDS.md", "source_location": "L289"}, {"id": "docs_development_standards_role_based_access", "label": "Role-Based Access", "file_type": "document", "source_file": "C:\\Users\\HP\\OneDrive\\Desktop\\Projects\\VS Code\\AroCord-HIMS\\care-harmony-hub\\docs\\DEVELOPMENT_STANDARDS.md", "source_location": "L299"}, {"id": "docs_development_standards_codeblock_14", "label": "code:typescript (// \u2705 Check permissions before showing UI)", "file_type": "document", "source_file": "C:\\Users\\HP\\OneDrive\\Desktop\\Projects\\VS Code\\AroCord-HIMS\\care-harmony-hub\\docs\\DEVELOPMENT_STANDARDS.md", "source_location": "L301"}, {"id": "docs_development_standards_testing_standards", "label": "\u2705 Testing Standards", "file_type": "document", "source_file": "C:\\Users\\HP\\OneDrive\\Desktop\\Projects\\VS Code\\AroCord-HIMS\\care-harmony-hub\\docs\\DEVELOPMENT_STANDARDS.md", "source_location": "L318"}, {"id": "docs_development_standards_unit_tests_with_vitest", "label": "Unit Tests with Vitest", "file_type": "document", "source_file": "C:\\Users\\HP\\OneDrive\\Desktop\\Projects\\VS Code\\AroCord-HIMS\\care-harmony-hub\\docs\\DEVELOPMENT_STANDARDS.md", "source_location": "L320"}, {"id": "docs_development_standards_codeblock_15", "label": "code:typescript (// \u2705 Test with proper mocks and assertions)", "file_type": "document", "source_file": "C:\\Users\\HP\\OneDrive\\Desktop\\Projects\\VS Code\\AroCord-HIMS\\care-harmony-hub\\docs\\DEVELOPMENT_STANDARDS.md", "source_location": "L322"}, {"id": "docs_development_standards_codeblock_16", "label": "code:bash (npm run test:unit           # All unit tests)", "file_type": "document", "source_file": "C:\\Users\\HP\\OneDrive\\Desktop\\Projects\\VS Code\\AroCord-HIMS\\care-harmony-hub\\docs\\DEVELOPMENT_STANDARDS.md", "source_location": "L349"}, {"id": "docs_development_standards_import_path_conventions", "label": "\ud83d\udce6 Import Path Conventions", "file_type": "document", "source_file": "C:\\Users\\HP\\OneDrive\\Desktop\\Projects\\VS Code\\AroCord-HIMS\\care-harmony-hub\\docs\\DEVELOPMENT_STANDARDS.md", "source_location": "L359"}, {"id": "docs_development_standards_use_alias_paths", "label": "\u2705 Use Alias Paths", "file_type": "document", "source_file": "C:\\Users\\HP\\OneDrive\\Desktop\\Projects\\VS Code\\AroCord-HIMS\\care-harmony-hub\\docs\\DEVELOPMENT_STANDARDS.md", "source_location": "L361"}, {"id": "docs_development_standards_codeblock_17", "label": "code:typescript (// \u2705 GOOD - Clear, maintainable)", "file_type": "document", "source_file": "C:\\Users\\HP\\OneDrive\\Desktop\\Projects\\VS Code\\AroCord-HIMS\\care-harmony-hub\\docs\\DEVELOPMENT_STANDARDS.md", "source_location": "L363"}, {"id": "docs_development_standards_codeblock_18", "label": "code:json ({)", "file_type": "document", "source_file": "C:\\Users\\HP\\OneDrive\\Desktop\\Projects\\VS Code\\AroCord-HIMS\\care-harmony-hub\\docs\\DEVELOPMENT_STANDARDS.md", "source_location": "L376"}, {"id": "docs_development_standards_performance_optimization", "label": "\ud83d\ude80 Performance Optimization", "file_type": "document", "source_file": "C:\\Users\\HP\\OneDrive\\Desktop\\Projects\\VS Code\\AroCord-HIMS\\care-harmony-hub\\docs\\DEVELOPMENT_STANDARDS.md", "source_location": "L386"}, {"id": "docs_development_standards_memoization", "label": "Memoization", "file_type": "document", "source_file": "C:\\Users\\HP\\OneDrive\\Desktop\\Projects\\VS Code\\AroCord-HIMS\\care-harmony-hub\\docs\\DEVELOPMENT_STANDARDS.md", "source_location": "L388"}, {"id": "docs_development_standards_codeblock_19", "label": "code:typescript (// \u2705 Memoize expensive computations)", "file_type": "document", "source_file": "C:\\Users\\HP\\OneDrive\\Desktop\\Projects\\VS Code\\AroCord-HIMS\\care-harmony-hub\\docs\\DEVELOPMENT_STANDARDS.md", "source_location": "L390"}, {"id": "docs_development_standards_code_splitting", "label": "Code Splitting", "file_type": "document", "source_file": "C:\\Users\\HP\\OneDrive\\Desktop\\Projects\\VS Code\\AroCord-HIMS\\care-harmony-hub\\docs\\DEVELOPMENT_STANDARDS.md", "source_location": "L403"}, {"id": "docs_development_standards_codeblock_20", "label": "code:typescript (// \u2705 Lazy-load less-critical routes)", "file_type": "document", "source_file": "C:\\Users\\HP\\OneDrive\\Desktop\\Projects\\VS Code\\AroCord-HIMS\\care-harmony-hub\\docs\\DEVELOPMENT_STANDARDS.md", "source_location": "L405"}, {"id": "docs_development_standards_documentation_in_code", "label": "\ud83d\udcc4 Documentation in Code", "file_type": "document", "source_file": "C:\\Users\\HP\\OneDrive\\Desktop\\Projects\\VS Code\\AroCord-HIMS\\care-harmony-hub\\docs\\DEVELOPMENT_STANDARDS.md", "source_location": "L418"}, {"id": "docs_development_standards_jsdoc_for_public_apis", "label": "JSDoc for Public APIs", "file_type": "document", "source_file": "C:\\Users\\HP\\OneDrive\\Desktop\\Projects\\VS Code\\AroCord-HIMS\\care-harmony-hub\\docs\\DEVELOPMENT_STANDARDS.md", "source_location": "L420"}, {"id": "docs_development_standards_codeblock_21", "label": "code:typescript (/**)", "file_type": "document", "source_file": "C:\\Users\\HP\\OneDrive\\Desktop\\Projects\\VS Code\\AroCord-HIMS\\care-harmony-hub\\docs\\DEVELOPMENT_STANDARDS.md", "source_location": "L422"}, {"id": "docs_development_standards_code_review_checklist", "label": "\ud83d\udeab Code Review Checklist", "file_type": "document", "source_file": "C:\\Users\\HP\\OneDrive\\Desktop\\Projects\\VS Code\\AroCord-HIMS\\care-harmony-hub\\docs\\DEVELOPMENT_STANDARDS.md", "source_location": "L445"}, {"id": "docs_development_standards_further_reading", "label": "Further Reading", "file_type": "document", "source_file": "C:\\Users\\HP\\OneDrive\\Desktop\\Projects\\VS Code\\AroCord-HIMS\\care-harmony-hub\\docs\\DEVELOPMENT_STANDARDS.md", "source_location": "L463"}], "edges": [{"source": "c_users_hp_onedrive_desktop_projects_vs_code_arocord_hims_care_harmony_hub_docs_development_standards_md", "target": "docs_development_standards_caresync_hims_development_standards_best_practices", "relation": "contains", "confidence": "EXTRACTED", "source_file": "C:\\Users\\HP\\OneDrive\\Desktop\\Projects\\VS Code\\AroCord-HIMS\\care-harmony-hub\\docs\\DEVELOPMENT_STANDARDS.md", "source_location": "L1", "weight": 1.0}, {"source": "docs_development_standards_caresync_hims_development_standards_best_practices", "target": "docs_development_standards_quick_navigation", "relation": "contains", "confidence": "EXTRACTED", "source_file": "C:\\Users\\HP\\OneDrive\\Desktop\\Projects\\VS Code\\AroCord-HIMS\\care-harmony-hub\\docs\\DEVELOPMENT_STANDARDS.md", "source_location": "L9", "weight": 1.0}, {"source": "docs_development_standards_caresync_hims_development_standards_best_practices", "target": "docs_development_standards_core_principles", "relation": "contains", "confidence": "EXTRACTED", "source_file": "C:\\Users\\HP\\OneDrive\\Desktop\\Projects\\VS Code\\AroCord-HIMS\\care-harmony-hub\\docs\\DEVELOPMENT_STANDARDS.md", "source_location": "L20", "weight": 1.0}, {"source": "docs_development_standards_core_principles", "target": "docs_development_standards_1_clean_code_solid", "relation": "contains", "confidence": "EXTRACTED", "source_file": "C:\\Users\\HP\\OneDrive\\Desktop\\Projects\\VS Code\\AroCord-HIMS\\care-harmony-hub\\docs\\DEVELOPMENT_STANDARDS.md", "source_location": "L22", "weight": 1.0}, {"source": "docs_development_standards_core_principles", "target": "docs_development_standards_2_type_safety", "relation": "contains", "confidence": "EXTRACTED", "source_file": "C:\\Users\\HP\\OneDrive\\Desktop\\Projects\\VS Code\\AroCord-HIMS\\care-harmony-hub\\docs\\DEVELOPMENT_STANDARDS.md", "source_location": "L28", "weight": 1.0}, {"source": "docs_development_standards_core_principles", "target": "docs_development_standards_3_error_handling_security", "relation": "contains", "confidence": "EXTRACTED", "source_file": "C:\\Users\\HP\\OneDrive\\Desktop\\Projects\\VS Code\\AroCord-HIMS\\care-harmony-hub\\docs\\DEVELOPMENT_STANDARDS.md", "source_location": "L34", "weight": 1.0}, {"source": "docs_development_standards_core_principles", "target": "docs_development_standards_4_performance", "relation": "contains", "confidence": "EXTRACTED", "source_file": "C:\\Users\\HP\\OneDrive\\Desktop\\Projects\\VS Code\\AroCord-HIMS\\care-harmony-hub\\docs\\DEVELOPMENT_STANDARDS.md", "source_location": "L40", "weight": 1.0}, {"source": "docs_development_standards_caresync_hims_development_standards_best_practices", "target": "docs_development_standards_code_style_guide", "relation": "contains", "confidence": "EXTRACTED", "source_file": "C:\\Users\\HP\\OneDrive\\Desktop\\Projects\\VS Code\\AroCord-HIMS\\care-harmony-hub\\docs\\DEVELOPMENT_STANDARDS.md", "source_location": "L48", "weight": 1.0}, {"source": "docs_development_standards_code_style_guide", "target": "docs_development_standards_typescript_configuration", "relation": "contains", "confidence": "EXTRACTED", "source_file": "C:\\Users\\HP\\OneDrive\\Desktop\\Projects\\VS Code\\AroCord-HIMS\\care-harmony-hub\\docs\\DEVELOPMENT_STANDARDS.md", "source_location": "L50", "weight": 1.0}, {"source": "docs_development_standards_typescript_configuration", "target": "docs_development_standards_codeblock_1", "relation": "contains", "confidence": "EXTRACTED", "source_file": "C:\\Users\\HP\\OneDrive\\Desktop\\Projects\\VS Code\\AroCord-HIMS\\care-harmony-hub\\docs\\DEVELOPMENT_STANDARDS.md", "source_location": "L53", "weight": 1.0}, {"source": "docs_development_standards_code_style_guide", "target": "docs_development_standards_naming_conventions", "relation": "contains", "confidence": "EXTRACTED", "source_file": "C:\\Users\\HP\\OneDrive\\Desktop\\Projects\\VS Code\\AroCord-HIMS\\care-harmony-hub\\docs\\DEVELOPMENT_STANDARDS.md", "source_location": "L68", "weight": 1.0}, {"source": "docs_development_standards_naming_conventions", "target": "docs_development_standards_components", "relation": "contains", "confidence": "EXTRACTED", "source_file": "C:\\Users\\HP\\OneDrive\\Desktop\\Projects\\VS Code\\AroCord-HIMS\\care-harmony-hub\\docs\\DEVELOPMENT_STANDARDS.md", "source_location": "L70", "weight": 1.0}, {"source": "docs_development_standards_components", "target": "docs_development_standards_codeblock_2", "relation": "contains", "confidence": "EXTRACTED", "source_file": "C:\\Users\\HP\\OneDrive\\Desktop\\Projects\\VS Code\\AroCord-HIMS\\care-harmony-hub\\docs\\DEVELOPMENT_STANDARDS.md", "source_location": "L71", "weight": 1.0}, {"source": "docs_development_standards_naming_conventions", "target": "docs_development_standards_hooks", "relation": "contains", "confidence": "EXTRACTED", "source_file": "C:\\Users\\HP\\OneDrive\\Desktop\\Projects\\VS Code\\AroCord-HIMS\\care-harmony-hub\\docs\\DEVELOPMENT_STANDARDS.md", "source_location": "L81", "weight": 1.0}, {"source": "docs_development_standards_hooks", "target": "docs_development_standards_codeblock_3", "relation": "contains", "confidence": "EXTRACTED", "source_file": "C:\\Users\\HP\\OneDrive\\Desktop\\Projects\\VS Code\\AroCord-HIMS\\care-harmony-hub\\docs\\DEVELOPMENT_STANDARDS.md", "source_location": "L82", "weight": 1.0}, {"source": "docs_development_standards_naming_conventions", "target": "docs_development_standards_types_interfaces", "relation": "contains", "confidence": "EXTRACTED", "source_file": "C:\\Users\\HP\\OneDrive\\Desktop\\Projects\\VS Code\\AroCord-HIMS\\care-harmony-hub\\docs\\DEVELOPMENT_STANDARDS.md", "source_location": "L93", "weight": 1.0}, {"source": "docs_development_standards_types_interfaces", "target": "docs_development_standards_codeblock_4", "relation": "contains", "confidence": "EXTRACTED", "source_file": "C:\\Users\\HP\\OneDrive\\Desktop\\Projects\\VS Code\\AroCord-HIMS\\care-harmony-hub\\docs\\DEVELOPMENT_STANDARDS.md", "source_location": "L94", "weight": 1.0}, {"source": "docs_development_standards_code_style_guide", "target": "docs_development_standards_file_organization", "relation": "contains", "confidence": "EXTRACTED", "source_file": "C:\\Users\\HP\\OneDrive\\Desktop\\Projects\\VS Code\\AroCord-HIMS\\care-harmony-hub\\docs\\DEVELOPMENT_STANDARDS.md", "source_location": "L111", "weight": 1.0}, {"source": "docs_development_standards_file_organization", "target": "docs_development_standards_component_structure", "relation": "contains", "confidence": "EXTRACTED", "source_file": "C:\\Users\\HP\\OneDrive\\Desktop\\Projects\\VS Code\\AroCord-HIMS\\care-harmony-hub\\docs\\DEVELOPMENT_STANDARDS.md", "source_location": "L113", "weight": 1.0}, {"source": "docs_development_standards_component_structure", "target": "docs_development_standards_codeblock_5", "relation": "contains", "confidence": "EXTRACTED", "source_file": "C:\\Users\\HP\\OneDrive\\Desktop\\Projects\\VS Code\\AroCord-HIMS\\care-harmony-hub\\docs\\DEVELOPMENT_STANDARDS.md", "source_location": "L114", "weight": 1.0}, {"source": "docs_development_standards_file_organization", "target": "docs_development_standards_hooks_structure", "relation": "contains", "confidence": "EXTRACTED", "source_file": "C:\\Users\\HP\\OneDrive\\Desktop\\Projects\\VS Code\\AroCord-HIMS\\care-harmony-hub\\docs\\DEVELOPMENT_STANDARDS.md", "source_location": "L134", "weight": 1.0}, {"source": "docs_development_standards_hooks_structure", "target": "docs_development_standards_codeblock_6", "relation": "contains", "confidence": "EXTRACTED", "source_file": "C:\\Users\\HP\\OneDrive\\Desktop\\Projects\\VS Code\\AroCord-HIMS\\care-harmony-hub\\docs\\DEVELOPMENT_STANDARDS.md", "source_location": "L135", "weight": 1.0}, {"source": "docs_development_standards_file_organization", "target": "docs_development_standards_utilities_structure", "relation": "contains", "confidence": "EXTRACTED", "source_file": "C:\\Users\\HP\\OneDrive\\Desktop\\Projects\\VS Code\\AroCord-HIMS\\care-harmony-hub\\docs\\DEVELOPMENT_STANDARDS.md", "source_location": "L144", "weight": 1.0}, {"source": "docs_development_standards_utilities_structure", "target": "docs_development_standards_codeblock_7", "relation": "contains", "confidence": "EXTRACTED", "source_file": "C:\\Users\\HP\\OneDrive\\Desktop\\Projects\\VS Code\\AroCord-HIMS\\care-harmony-hub\\docs\\DEVELOPMENT_STANDARDS.md", "source_location": "L145", "weight": 1.0}, {"source": "docs_development_standards_caresync_hims_development_standards_best_practices", "target": "docs_development_standards_react_component_patterns", "relation": "contains", "confidence": "EXTRACTED", "source_file": "C:\\Users\\HP\\OneDrive\\Desktop\\Projects\\VS Code\\AroCord-HIMS\\care-harmony-hub\\docs\\DEVELOPMENT_STANDARDS.md", "source_location": "L154", "weight": 1.0}, {"source": "docs_development_standards_react_component_patterns", "target": "docs_development_standards_functional_component_with_hooks", "relation": "contains", "confidence": "EXTRACTED", "source_file": "C:\\Users\\HP\\OneDrive\\Desktop\\Projects\\VS Code\\AroCord-HIMS\\care-harmony-hub\\docs\\DEVELOPMENT_STANDARDS.md", "source_location": "L156", "weight": 1.0}, {"source": "docs_development_standards_functional_component_with_hooks", "target": "docs_development_standards_codeblock_8", "relation": "contains", "confidence": "EXTRACTED", "source_file": "C:\\Users\\HP\\OneDrive\\Desktop\\Projects\\VS Code\\AroCord-HIMS\\care-harmony-hub\\docs\\DEVELOPMENT_STANDARDS.md", "source_location": "L158", "weight": 1.0}, {"source": "docs_development_standards_react_component_patterns", "target": "docs_development_standards_form_component_with_validation", "relation": "contains", "confidence": "EXTRACTED", "source_file": "C:\\Users\\HP\\OneDrive\\Desktop\\Projects\\VS Code\\AroCord-HIMS\\care-harmony-hub\\docs\\DEVELOPMENT_STANDARDS.md", "source_location": "L181", "weight": 1.0}, {"source": "docs_development_standards_form_component_with_validation", "target": "docs_development_standards_codeblock_9", "relation": "contains", "confidence": "EXTRACTED", "source_file": "C:\\Users\\HP\\OneDrive\\Desktop\\Projects\\VS Code\\AroCord-HIMS\\care-harmony-hub\\docs\\DEVELOPMENT_STANDARDS.md", "source_location": "L184", "weight": 1.0}, {"source": "docs_development_standards_caresync_hims_development_standards_best_practices", "target": "docs_development_standards_data_fetching_state_management", "relation": "contains", "confidence": "EXTRACTED", "source_file": "C:\\Users\\HP\\OneDrive\\Desktop\\Projects\\VS Code\\AroCord-HIMS\\care-harmony-hub\\docs\\DEVELOPMENT_STANDARDS.md", "source_location": "L211", "weight": 1.0}, {"source": "docs_development_standards_data_fetching_state_management", "target": "docs_development_standards_using_tanstack_query_react_query", "relation": "contains", "confidence": "EXTRACTED", "source_file": "C:\\Users\\HP\\OneDrive\\Desktop\\Projects\\VS Code\\AroCord-HIMS\\care-harmony-hub\\docs\\DEVELOPMENT_STANDARDS.md", "source_location": "L213", "weight": 1.0}, {"source": "docs_development_standards_using_tanstack_query_react_query", "target": "docs_development_standards_codeblock_10", "relation": "contains", "confidence": "EXTRACTED", "source_file": "C:\\Users\\HP\\OneDrive\\Desktop\\Projects\\VS Code\\AroCord-HIMS\\care-harmony-hub\\docs\\DEVELOPMENT_STANDARDS.md", "source_location": "L215", "weight": 1.0}, {"source": "docs_development_standards_data_fetching_state_management", "target": "docs_development_standards_error_handling", "relation": "contains", "confidence": "EXTRACTED", "source_file": "C:\\Users\\HP\\OneDrive\\Desktop\\Projects\\VS Code\\AroCord-HIMS\\care-harmony-hub\\docs\\DEVELOPMENT_STANDARDS.md", "source_location": "L243", "weight": 1.0}, {"source": "docs_development_standards_error_handling", "target": "docs_development_standards_codeblock_11", "relation": "contains", "confidence": "EXTRACTED", "source_file": "C:\\Users\\HP\\OneDrive\\Desktop\\Projects\\VS Code\\AroCord-HIMS\\care-harmony-hub\\docs\\DEVELOPMENT_STANDARDS.md", "source_location": "L245", "weight": 1.0}, {"source": "docs_development_standards_caresync_hims_development_standards_best_practices", "target": "docs_development_standards_security_hipaa", "relation": "contains", "confidence": "EXTRACTED", "source_file": "C:\\Users\\HP\\OneDrive\\Desktop\\Projects\\VS Code\\AroCord-HIMS\\care-harmony-hub\\docs\\DEVELOPMENT_STANDARDS.md", "source_location": "L273", "weight": 1.0}, {"source": "docs_development_standards_security_hipaa", "target": "docs_development_standards_input_sanitization", "relation": "contains", "confidence": "EXTRACTED", "source_file": "C:\\Users\\HP\\OneDrive\\Desktop\\Projects\\VS Code\\AroCord-HIMS\\care-harmony-hub\\docs\\DEVELOPMENT_STANDARDS.md", "source_location": "L275", "weight": 1.0}, {"source": "docs_development_standards_input_sanitization", "target": "docs_development_standards_codeblock_12", "relation": "contains", "confidence": "EXTRACTED", "source_file": "C:\\Users\\HP\\OneDrive\\Desktop\\Projects\\VS Code\\AroCord-HIMS\\care-harmony-hub\\docs\\DEVELOPMENT_STANDARDS.md", "source_location": "L277", "weight": 1.0}, {"source": "docs_development_standards_security_hipaa", "target": "docs_development_standards_phi_protection", "relation": "contains", "confidence": "EXTRACTED", "source_file": "C:\\Users\\HP\\OneDrive\\Desktop\\Projects\\VS Code\\AroCord-HIMS\\care-harmony-hub\\docs\\DEVELOPMENT_STANDARDS.md", "source_location": "L287", "weight": 1.0}, {"source": "docs_development_standards_phi_protection", "target": "docs_development_standards_codeblock_13", "relation": "contains", "confidence": "EXTRACTED", "source_file": "C:\\Users\\HP\\OneDrive\\Desktop\\Projects\\VS Code\\AroCord-HIMS\\care-harmony-hub\\docs\\DEVELOPMENT_STANDARDS.md", "source_location": "L289", "weight": 1.0}, {"source": "docs_development_standards_security_hipaa", "target": "docs_development_standards_role_based_access", "relation": "contains", "confidence": "EXTRACTED", "source_file": "C:\\Users\\HP\\OneDrive\\Desktop\\Projects\\VS Code\\AroCord-HIMS\\care-harmony-hub\\docs\\DEVELOPMENT_STANDARDS.md", "source_location": "L299", "weight": 1.0}, {"source": "docs_development_standards_role_based_access", "target": "docs_development_standards_codeblock_14", "relation": "contains", "confidence": "EXTRACTED", "source_file": "C:\\Users\\HP\\OneDrive\\Desktop\\Projects\\VS Code\\AroCord-HIMS\\care-harmony-hub\\docs\\DEVELOPMENT_STANDARDS.md", "source_location": "L301", "weight": 1.0}, {"source": "docs_development_standards_caresync_hims_development_standards_best_practices", "target": "docs_development_standards_testing_standards", "relation": "contains", "confidence": "EXTRACTED", "source_file": "C:\\Users\\HP\\OneDrive\\Desktop\\Projects\\VS Code\\AroCord-HIMS\\care-harmony-hub\\docs\\DEVELOPMENT_STANDARDS.md", "source_location": "L318", "weight": 1.0}, {"source": "docs_development_standards_testing_standards", "target": "docs_development_standards_unit_tests_with_vitest", "relation": "contains", "confidence": "EXTRACTED", "source_file": "C:\\Users\\HP\\OneDrive\\Desktop\\Projects\\VS Code\\AroCord-HIMS\\care-harmony-hub\\docs\\DEVELOPMENT_STANDARDS.md", "source_location": "L320", "weight": 1.0}, {"source": "docs_development_standards_unit_tests_with_vitest", "target": "docs_development_standards_codeblock_15", "relation": "contains", "confidence": "EXTRACTED", "source_file": "C:\\Users\\HP\\OneDrive\\Desktop\\Projects\\VS Code\\AroCord-HIMS\\care-harmony-hub\\docs\\DEVELOPMENT_STANDARDS.md", "source_location": "L322", "weight": 1.0}, {"source": "docs_development_standards_unit_tests_with_vitest", "target": "docs_development_standards_codeblock_16", "relation": "contains", "confidence": "EXTRACTED", "source_file": "C:\\Users\\HP\\OneDrive\\Desktop\\Projects\\VS Code\\AroCord-HIMS\\care-harmony-hub\\docs\\DEVELOPMENT_STANDARDS.md", "source_location": "L349", "weight": 1.0}, {"source": "docs_development_standards_caresync_hims_development_standards_best_practices", "target": "docs_development_standards_import_path_conventions", "relation": "contains", "confidence": "EXTRACTED", "source_file": "C:\\Users\\HP\\OneDrive\\Desktop\\Projects\\VS Code\\AroCord-HIMS\\care-harmony-hub\\docs\\DEVELOPMENT_STANDARDS.md", "source_location": "L359", "weight": 1.0}, {"source": "docs_development_standards_import_path_conventions", "target": "docs_development_standards_use_alias_paths", "relation": "contains", "confidence": "EXTRACTED", "source_file": "C:\\Users\\HP\\OneDrive\\Desktop\\Projects\\VS Code\\AroCord-HIMS\\care-harmony-hub\\docs\\DEVELOPMENT_STANDARDS.md", "source_location": "L361", "weight": 1.0}, {"source": "docs_development_standards_use_alias_paths", "target": "docs_development_standards_codeblock_17", "relation": "contains", "confidence": "EXTRACTED", "source_file": "C:\\Users\\HP\\OneDrive\\Desktop\\Projects\\VS Code\\AroCord-HIMS\\care-harmony-hub\\docs\\DEVELOPMENT_STANDARDS.md", "source_location": "L363", "weight": 1.0}, {"source": "docs_development_standards_use_alias_paths", "target": "docs_development_standards_codeblock_18", "relation": "contains", "confidence": "EXTRACTED", "source_file": "C:\\Users\\HP\\OneDrive\\Desktop\\Projects\\VS Code\\AroCord-HIMS\\care-harmony-hub\\docs\\DEVELOPMENT_STANDARDS.md", "source_location": "L376", "weight": 1.0}, {"source": "docs_development_standards_caresync_hims_development_standards_best_practices", "target": "docs_development_standards_performance_optimization", "relation": "contains", "confidence": "EXTRACTED", "source_file": "C:\\Users\\HP\\OneDrive\\Desktop\\Projects\\VS Code\\AroCord-HIMS\\care-harmony-hub\\docs\\DEVELOPMENT_STANDARDS.md", "source_location": "L386", "weight": 1.0}, {"source": "docs_development_standards_performance_optimization", "target": "docs_development_standards_memoization", "relation": "contains", "confidence": "EXTRACTED", "source_file": "C:\\Users\\HP\\OneDrive\\Desktop\\Projects\\VS Code\\AroCord-HIMS\\care-harmony-hub\\docs\\DEVELOPMENT_STANDARDS.md", "source_location": "L388", "weight": 1.0}, {"source": "docs_development_standards_memoization", "target": "docs_development_standards_codeblock_19", "relation": "contains", "confidence": "EXTRACTED", "source_file": "C:\\Users\\HP\\OneDrive\\Desktop\\Projects\\VS Code\\AroCord-HIMS\\care-harmony-hub\\docs\\DEVELOPMENT_STANDARDS.md", "source_location": "L390", "weight": 1.0}, {"source": "docs_development_standards_performance_optimization", "target": "docs_development_standards_code_splitting", "relation": "contains", "confidence": "EXTRACTED", "source_file": "C:\\Users\\HP\\OneDrive\\Desktop\\Projects\\VS Code\\AroCord-HIMS\\care-harmony-hub\\docs\\DEVELOPMENT_STANDARDS.md", "source_location": "L403", "weight": 1.0}, {"source": "docs_development_standards_code_splitting", "target": "docs_development_standards_codeblock_20", "relation": "contains", "confidence": "EXTRACTED", "source_file": "C:\\Users\\HP\\OneDrive\\Desktop\\Projects\\VS Code\\AroCord-HIMS\\care-harmony-hub\\docs\\DEVELOPMENT_STANDARDS.md", "source_location": "L405", "weight": 1.0}, {"source": "docs_development_standards_caresync_hims_development_standards_best_practices", "target": "docs_development_standards_documentation_in_code", "relation": "contains", "confidence": "EXTRACTED", "source_file": "C:\\Users\\HP\\OneDrive\\Desktop\\Projects\\VS Code\\AroCord-HIMS\\care-harmony-hub\\docs\\DEVELOPMENT_STANDARDS.md", "source_location": "L418", "weight": 1.0}, {"source": "docs_development_standards_documentation_in_code", "target": "docs_development_standards_jsdoc_for_public_apis", "relation": "contains", "confidence": "EXTRACTED", "source_file": "C:\\Users\\HP\\OneDrive\\Desktop\\Projects\\VS Code\\AroCord-HIMS\\care-harmony-hub\\docs\\DEVELOPMENT_STANDARDS.md", "source_location": "L420", "weight": 1.0}, {"source": "docs_development_standards_jsdoc_for_public_apis", "target": "docs_development_standards_codeblock_21", "relation": "contains", "confidence": "EXTRACTED", "source_file": "C:\\Users\\HP\\OneDrive\\Desktop\\Projects\\VS Code\\AroCord-HIMS\\care-harmony-hub\\docs\\DEVELOPMENT_STANDARDS.md", "source_location": "L422", "weight": 1.0}, {"source": "docs_development_standards_caresync_hims_development_standards_best_practices", "target": "docs_development_standards_code_review_checklist", "relation": "contains", "confidence": "EXTRACTED", "source_file": "C:\\Users\\HP\\OneDrive\\Desktop\\Projects\\VS Code\\AroCord-HIMS\\care-harmony-hub\\docs\\DEVELOPMENT_STANDARDS.md", "source_location": "L445", "weight": 1.0}, {"source": "docs_development_standards_caresync_hims_development_standards_best_practices", "target": "docs_development_standards_further_reading", "relation": "contains", "confidence": "EXTRACTED", "source_file": "C:\\Users\\HP\\OneDrive\\Desktop\\Projects\\VS Code\\AroCord-HIMS\\care-harmony-hub\\docs\\DEVELOPMENT_STANDARDS.md", "source_location": "L463", "weight": 1.0}], "input_tokens": 0, "output_tokens": 0}